MANIFEST.in
README.md
setup.py
capsule/__init__.py
capsule/core.py
capsule/data.py
capsule/download.py
capsule_cli.egg-info/PKG-INFO
capsule_cli.egg-info/SOURCES.txt
capsule_cli.egg-info/dependency_links.txt
capsule_cli.egg-info/entry_points.txt
capsule_cli.egg-info/requires.txt
capsule_cli.egg-info/top_level.txt