Metadata-Version: 1.1
Name: capsule-cli
Version: 1.0.1
Summary: Bookmark and clone your favorite code.
Home-page: https://github.com/sourcepirate/capsule.git
Author: sourcepirate
Author-email: plasmashadowx@gmail.com
License: MIT
Platform: UNKNOWN
Classifier: Programming Language :: Python
Classifier: License :: OSI Approved :: GNU General Public License (GPL)
